odsbox_jaquel_mcp/__init__.py
odsbox_jaquel_mcp/__main__.py
odsbox_jaquel_mcp/bulk_api_guide.py
odsbox_jaquel_mcp/connection.py
odsbox_jaquel_mcp/data_preparation.py
odsbox_jaquel_mcp/measurement_analysis.py
odsbox_jaquel_mcp/measurement_queries.py
odsbox_jaquel_mcp/notebook_generator.py
odsbox_jaquel_mcp/prompts.py
odsbox_jaquel_mcp/queries.py
odsbox_jaquel_mcp/resources.py
odsbox_jaquel_mcp/schemas.py
odsbox_jaquel_mcp/schemas_entity_descriptions.py
odsbox_jaquel_mcp/server.py
odsbox_jaquel_mcp/server_instructions.md
odsbox_jaquel_mcp/validators.py
odsbox_jaquel_mcp/visualization_templates.py
odsbox_jaquel_mcp/resource_files/__init__.py
odsbox_jaquel_mcp/resource_files/resource_connection_troubleshooting.md
odsbox_jaquel_mcp/resource_files/resource_jaquel_syntax_guide.md
odsbox_jaquel_mcp/resource_files/resource_ods_connection_guide.md
odsbox_jaquel_mcp/resource_files/resource_ods_entity_hierarchy.md
odsbox_jaquel_mcp/resource_files/resource_ods_workflow_reference.md
odsbox_jaquel_mcp/resource_files/resource_query_execution_patterns.md
odsbox_jaquel_mcp/resource_files/resource_query_operators_reference.md
odsbox_jaquel_mcp/submatrix/__init__.py
odsbox_jaquel_mcp/submatrix/data_reader.py
odsbox_jaquel_mcp/submatrix/scripts.py
odsbox_jaquel_mcp/templates/__init__.j2
odsbox_jaquel_mcp/templates/advanced_fetcher.j2
odsbox_jaquel_mcp/templates/analysis_fetcher.j2
odsbox_jaquel_mcp/templates/basic_fetcher.j2
odsbox_jaquel_mcp/templates/batch_fetcher.j2
odsbox_jaquel_mcp/templates/notebook_plot_line.j2
odsbox_jaquel_mcp/templates/notebook_plot_scatter.j2
odsbox_jaquel_mcp/templates/notebook_preparation.j2
odsbox_jaquel_mcp/templates/notebook_retrieval.j2
odsbox_jaquel_mcp/templates/visualization_line.j2
odsbox_jaquel_mcp/templates/visualization_scatter.j2
odsbox_jaquel_mcp/templates/visualization_subplots.j2
odsbox_jaquel_mcp/tools/__init__.py
odsbox_jaquel_mcp/tools/base_handler.py
odsbox_jaquel_mcp/tools/connection_tools.py
odsbox_jaquel_mcp/tools/help_tools.py
odsbox_jaquel_mcp-1.1.1.dist-info/licenses/LICENSE
odsbox_jaquel_mcp-1.1.1.dist-info/METADATA
odsbox_jaquel_mcp-1.1.1.dist-info/WHEEL
odsbox_jaquel_mcp-1.1.1.dist-info/entry_points.txt
odsbox_jaquel_mcp-1.1.1.dist-info/top_level.txt
odsbox_jaquel_mcp-1.1.1.dist-info/RECORD
