Metadata-Version: 2.4
Name: odsbox-jaquel-mcp
Version: 1.1.1
Summary: ASAM ODS MCP Server - Query and analyze measurement data from ASAM ODS servers in AI agent systems.
Author-email: Andreas K <totonga@gmail.com>
License: Apache-2.0
Project-URL: Homepage, https://github.com/totonga/odsbox-jaquel-mcp/tree/main#readme
Project-URL: Documentation, https://github.com/totonga/odsbox-jaquel-mcp/tree/main#readme
Project-URL: Repository, https://github.com/totonga/odsbox-jaquel-mcp
Project-URL: Tracker, https://github.com/totonga/odsbox-jaquel-mcp/issues
Project-URL: Changelog, https://github.com/totonga/odsbox-jaquel-mcp/blob/main/CHANGELOG.md
Keywords: mcp,jaquel,odsbox,asam,ods,measurement,data access,data science,data analysis
Classifier: Development Status :: 3 - Alpha
Classifier: Intended Audience :: Science/Research
Classifier: License :: OSI Approved :: Apache Software License
Classifier: Operating System :: OS Independent
Classifier: Programming Language :: Python :: 3
Classifier: Programming Language :: Python :: 3.13
Classifier: Topic :: Software Development :: Libraries :: Python Modules
Classifier: Topic :: Scientific/Engineering :: Information Analysis
Classifier: Topic :: Scientific/Engineering :: Interface Engine/Protocol Translator
Classifier: Topic :: System :: Monitoring
Classifier: Topic :: Database :: Front-Ends
Requires-Python: >=3.13
License-File: LICENSE
Requires-Dist: mcp>=0.1.0
Requires-Dist: odsbox>=1.0.15
Requires-Dist: pip-system-certs
Requires-Dist: matplotlib
Requires-Dist: Jinja2>=3.0
Provides-Extra: dev
Requires-Dist: pytest>=7.0; extra == "dev"
Requires-Dist: pytest-asyncio>=1.2.0; extra == "dev"
Requires-Dist: black>=23.0; extra == "dev"
Requires-Dist: isort>=5.0; extra == "dev"
Requires-Dist: flake8>=6.0; extra == "dev"
Requires-Dist: mypy>=1.0; extra == "dev"
Requires-Dist: build>=0.8.0; extra == "dev"
Requires-Dist: pandas-stubs>=2.3; extra == "dev"
Requires-Dist: python-semantic-release>=10.5.3; extra == "dev"
Requires-Dist: pre-commit>=3.0; extra == "dev"
Provides-Extra: lint
Requires-Dist: commitlint>=19.0; extra == "lint"
Provides-Extra: play
Requires-Dist: flask; extra == "play"
Requires-Dist: plotly; extra == "play"
Requires-Dist: seaborn; extra == "play"
Requires-Dist: scipy; extra == "play"
Requires-Dist: PyQt5; extra == "play"
Requires-Dist: jupyter; extra == "play"
Dynamic: license-file
